spotfire/__init__.py
spotfire/_utils.py
spotfire/cabfile.cpython-312-x86_64-linux-gnu.so
spotfire/cabfile.pyi
spotfire/cabfile.pyx
spotfire/cabfile_helpers.c
spotfire/cabfile_helpers.h
spotfire/cabfile_helpers.pxi
spotfire/cabfile_windows.pyx
spotfire/codesign.cpython-312-x86_64-linux-gnu.so
spotfire/codesign.pyi
spotfire/codesign.pyx
spotfire/codesign_windows.pyx
spotfire/data_function.py
spotfire/public.py
spotfire/sbdf.cpython-312-x86_64-linux-gnu.so
spotfire/sbdf.pyi
spotfire/sbdf.pyx
spotfire/sbdf_helpers.c
spotfire/sbdf_helpers.h
spotfire/sbdf_helpers.pxi
spotfire/spk.py
spotfire/support.py
spotfire/version.py
spotfire/test/__init__.py
spotfire/test/__main__.py
spotfire/test/test_cabfile.py
spotfire/test/test_data_function.py
spotfire/test/test_sbdf.py
spotfire/test/utils.py
spotfire-2.4.0.dist-info/METADATA
spotfire-2.4.0.dist-info/WHEEL
spotfire-2.4.0.dist-info/top_level.txt
spotfire-2.4.0.dist-info/RECORD
spotfire-2.4.0.dist-info/licenses/LICENSE
